sellpass/__init__.py
sellpass/announcements.py
sellpass/blacklist.py
sellpass/categories.py
sellpass/coupons.py
sellpass/customers.py
sellpass/customization.py
sellpass/dashboard.py
sellpass/faqs.py
sellpass/feedback.py
sellpass/groups.py
sellpass/listings.py
sellpass/orders.py
sellpass/products.py
sellpass/productsv2.py
sellpass/public.py
sellpass/shop.py
sellpass/tickets.py
sellpass-1.0.dist-info/METADATA
sellpass-1.0.dist-info/WHEEL
sellpass-1.0.dist-info/top_level.txt
sellpass-1.0.dist-info/RECORD
